statdepth/__init__.py
statdepth/depth/__init__.py
statdepth/depth/abstract.py
statdepth/depth/depth.py
statdepth/depth/prob_depth.py
statdepth/depth/calculations/__init__.py
statdepth/depth/calculations/_containment.py
statdepth/depth/calculations/_functional.py
statdepth/depth/calculations/_helper.py
statdepth/depth/calculations/_pointcloud.py
statdepth/depth/calculations/_uncertainty.py
statdepth/homogeneity/__init__.py
statdepth/homogeneity/homogeneity.py
statdepth/testing/__init__.py
statdepth/testing/_generating.py
statdepth-1.0.0.dist-info/AUTHORS.rst
statdepth-1.0.0.dist-info/LICENSE
statdepth-1.0.0.dist-info/METADATA
statdepth-1.0.0.dist-info/WHEEL
statdepth-1.0.0.dist-info/top_level.txt
statdepth-1.0.0.dist-info/RECORD
