Metadata-Version: 2.1
Name: statdepth
Version: 1.0.0
Summary: A library for computing statistical depth for univariate and multivariate functional data, and pointcloud data. Additionally, methods for homogeneity testing and visualization are provided.
Home-page: https://github.com/braingeneers/statdepth
Author: Julian Lehrer
Author-email: jmlehrer@ucsc.edu
License: GPL license
Keywords: statdepth
Platform: UNKNOWN
Classifier: Development Status :: 3 - Alpha
Classifier: Intended Audience :: Developers
Classifier: License :: OSI Approved :: GNU General Public License v2 (GPLv2)
Classifier: Natural Language :: English
Classifier: Programming Language :: Python :: 3
Classifier: Programming Language :: Python :: 3.6
Classifier: Programming Language :: Python :: 3.7
Classifier: Programming Language :: Python :: 3.8
Requires-Python: >=3.6
License-File: LICENSE
License-File: AUTHORS.rst
Requires-Dist: plotly
Requires-Dist: pandas
Requires-Dist: numpy
Requires-Dist: scipy
Requires-Dist: tqdm
